{
    "nodeID": 18,
    "in": {
        "2.0": {
            "1.0": 90.0,
            "2.0": 297577.0
        },
        "4.0": {
            "2.0": 120.0,
            "6.0": 49500.0
        },
        "6.0": {
            "2.0": 2166.0
        },
        "7.0": {
            "6.0": 2.0,
            "2.0": 2900.0
        },
        "9.0": {
            "1.0": 15.0,
            "2.0": 27200.0,
            "6.0": 2154.0
        },
        "10.0": {
            "2.0": 17113.0
        },
        "12.0": {
            "2.0": 5640.0,
            "6.0": 100.0
        },
        "13.0": {
            "2.0": 250.0
        },
        "14.0": {
            "1.0": 4.0,
            "2.0": 105.0,
            "6.0": 120.0
        },
        "18.0": {
            "2.0": 6900.0,
            "6.0": 1.0
        },
        "19.0": {
            "2.0": 100426.0,
            "6.0": 7.0
        },
        "21.0": {
            "2.0": 26441.0,
            "6.0": 8.0
        },
        "22.0": {
            "1.0": 189.0,
            "2.0": 269871.0,
            "6.0": 1614.0,
            "7.0": 210.0
        },
        "1.0": {
            "2.0": 2000.0
        },
        "3.0": {
            "2.0": 5.0
        },
        "8.0": {
            "2.0": 14.0,
            "6.0": 3.0
        },
        "11.0": {
            "6.0": 200.0
        },
        "17.0": {
            "2.0": 3100.0,
            "6.0": 1025.0
        }
    },
    "out": {
        "2.0": {
            "1.0": 30.0,
            "2.0": 40405.0,
            "6.0": 71296.0
        },
        "4.0": {
            "2.0": 23030.0,
            "6.0": 49600.0,
            "7.0": 50.0
        },
        "6.0": {
            "2.0": 955.0,
            "6.0": 20.0
        },
        "7.0": {
            "2.0": 1300.0,
            "6.0": 12.0,
            "3.0": 20.0
        },
        "8.0": {
            "6.0": 4.0,
            "2.0": 1178.0
        },
        "9.0": {
            "2.0": 30052.0,
            "6.0": 1.0
        },
        "10.0": {
            "2.0": 33175.0,
            "6.0": 131.0
        },
        "12.0": {
            "2.0": 20550.0,
            "6.0": 7.0
        },
        "13.0": {
            "2.0": 350.0
        },
        "14.0": {
            "2.0": 1760.0
        },
        "17.0": {
            "1.0": 4.0,
            "2.0": 30000.0,
            "6.0": 1000.0
        },
        "18.0": {
            "2.0": 22860.0,
            "6.0": 9.0
        },
        "19.0": {
            "2.0": 3716.0,
            "6.0": 101.0
        },
        "21.0": {
            "1.0": 208.0
        },
        "22.0": {
            "1.0": 314.0,
            "2.0": 352273.0,
            "6.0": 3768.0,
            "7.0": 50.0
        },
        "1.0": {
            "6.0": 8.0
        }
    }
}